ai_chunking/__init__.py
ai_chunking/chunkers/auto_ai_chunker/__init__.py
ai_chunking/chunkers/auto_ai_chunker/chunk_builder.py
ai_chunking/chunkers/auto_ai_chunker/models/document.py
ai_chunking/chunkers/auto_ai_chunker/models/llm_responses.py
ai_chunking/chunkers/auto_ai_chunker/processor.py
ai_chunking/chunkers/auto_ai_chunker/prompts.py
ai_chunking/chunkers/auto_ai_chunker/text_enricher.py
ai_chunking/chunkers/base_chunker.py
ai_chunking/chunkers/recursive_text_splitting_chunker/__init__.py
ai_chunking/chunkers/section_based_semantic_chunker/__init__.py
ai_chunking/chunkers/section_based_semantic_chunker/models.py
ai_chunking/chunkers/section_based_semantic_chunker/processors.py
ai_chunking/chunkers/section_based_semantic_chunker/prompts.py
ai_chunking/chunkers/section_based_semantic_chunker/semantic_chunker.py
ai_chunking/chunkers/section_based_semantic_chunker/utils.py
ai_chunking/chunkers/semantic_chunker/__init__.py
ai_chunking/llm/adapter.py
ai_chunking/llm/base.py
ai_chunking/llm/cache.py
ai_chunking/llm/factory.py
ai_chunking/llm/models.py
ai_chunking/llm/providers/__init__.py
ai_chunking/llm/providers/anthropic.py
ai_chunking/llm/providers/cohere.py
ai_chunking/llm/providers/gemini.py
ai_chunking/llm/providers/groq.py
ai_chunking/llm/providers/litellm.py
ai_chunking/llm/providers/openai.py
ai_chunking/llm/providers/vertex.py
ai_chunking/models/chunk.py
ai_chunking/module.py
ai_chunking/utils/__init__.py
ai_chunking/utils/count_tokens.py
ai_chunking/utils/json_utils.py
ai_chunking/utils/logging.py
ai_chunking/utils/markdown_utils.py
ai_chunking/utils/pdf_to_markdown.py
ai_chunking-0.1.9.dist-info/LICENSE
ai_chunking-0.1.9.dist-info/METADATA
ai_chunking-0.1.9.dist-info/WHEEL
ai_chunking-0.1.9.dist-info/RECORD
