Metadata-Version: 2.3
Name: ai-chunking
Version: 0.1.9
Summary: A powerful Python library for semantic document chunking and enrichment using AI
License: MIT
Keywords: ai,nlp,document-processing,chunking,semantic-analysis,rag,embeddings
Author: Amey Desai
Author-email: amey.desai@nexla.com
Requires-Python: >=3.9,<4.0
Classifier: Development Status :: 3 - Alpha
Classifier: Intended Audience :: Developers
Classifier: License :: OSI Approved :: MIT License
Classifier: Programming Language :: Python :: 3
Classifier: Programming Language :: Python :: 3.9
Classifier: Programming Language :: Python :: 3.10
Classifier: Programming Language :: Python :: 3.11
Classifier: Programming Language :: Python :: 3.12
Classifier: Programming Language :: Python :: 3.13
Classifier: Topic :: Software Development :: Libraries :: Python Modules
Classifier: Topic :: Text Processing :: General
Requires-Dist: aiohttp (>=3.8.0)
Requires-Dist: anthropic
Requires-Dist: cohere (>=4.48)
Requires-Dist: diskcache (>=5.6.0)
Requires-Dist: google-generativeai
Requires-Dist: groq (>=0.18.0)
Requires-Dist: instructor
Requires-Dist: jsonref
Requires-Dist: langchain (>=0.2.0)
Requires-Dist: langchain-experimental
Requires-Dist: langchain-openai
Requires-Dist: langchain_text_splitters
Requires-Dist: litellm
Requires-Dist: openai (>=1.0.0)
Requires-Dist: pydantic (>=2.0.0)
Requires-Dist: python-dotenv
Requires-Dist: tiktoken (>=0.5.0)
Requires-Dist: tqdm
Requires-Dist: vertexai (>=1.71.1)
Project-URL: Documentation, https://github.com/nexla-opensource/ai-chunking
Project-URL: Homepage, https://github.com/nexla-opensource/ai-chunking
Project-URL: Repository, https://github.com/nexla-opensource/ai-chunking.git
